graphing_lib/__init__.py
graphing_lib/api_contract.py
graphing_lib/expression_parser.py
graphing_lib/marching_cubes.py
graphing_lib/render.py
graphing_calculator_3d-0.1.2.dist-info/METADATA
graphing_calculator_3d-0.1.2.dist-info/WHEEL
graphing_calculator_3d-0.1.2.dist-info/top_level.txt
graphing_calculator_3d-0.1.2.dist-info/RECORD
