Metadata-Version: 2.4
Name: graphing_calculator_3d
Version: 0.1.2
Summary: A 3D/4D graphing library using VisPy and SymPy
Author-email: Yosef Gizachew <yeyeadmss@gmail.com>
Project-URL: Homepage, https://github.com/yosefgizachew/3D-graphing-calculator
Classifier: Programming Language :: Python :: 3
Classifier: License :: OSI Approved :: MIT License
Classifier: Operating System :: OS Independent
Requires-Python: >=3.8
Requires-Dist: numpy
Requires-Dist: sympy
Requires-Dist: vispy
Requires-Dist: scikit-image
Requires-Dist: PyQt5
